owcustom/sphinx/theme/VERSION
owcustom/sphinx/theme/__init__.py
owcustom/sphinx/theme/footer.html
owcustom/sphinx/theme/theme.conf
owcustom/sphinx/theme/static/css/owcustom.css
owcustom/sphinx/theme/static/js/theme.js
owcustom_sphinx_theme-1.0.0.dist-info/LICENSE
owcustom_sphinx_theme-1.0.0.dist-info/METADATA
owcustom_sphinx_theme-1.0.0.dist-info/WHEEL
owcustom_sphinx_theme-1.0.0.dist-info/entry_points.txt
owcustom_sphinx_theme-1.0.0.dist-info/top_level.txt
owcustom_sphinx_theme-1.0.0.dist-info/RECORD
