Metadata-Version: 2.1
Name: owcustom-sphinx-theme
Version: 1.0.0
Summary: owcustom theme for Sphinx and Read The Docs
Author: owcustom
Author-email: aryamanz29@gmail.com
License: MIT
Classifier: Framework :: Sphinx
Classifier: Framework :: Sphinx :: Theme
Classifier: Development Status :: 5 - Production/Stable
Classifier: License :: OSI Approved :: MIT License
Classifier: Environment :: Console
Classifier: Environment :: Web Environment
Classifier: Intended Audience :: Developers
Classifier: Operating System :: OS Independent
Classifier: Topic :: Documentation
Classifier: Topic :: Software Development :: Documentation
License-File: LICENSE
Requires-Dist: sphinx-rtd-theme (>=1.0.0)
Requires-Dist: sphinx-copybutton
